bluepyefe/__init__.py
bluepyefe/auto_targets.py
bluepyefe/cell.py
bluepyefe/extract.py
bluepyefe/nwbreader.py
bluepyefe/plotting.py
bluepyefe/protocol.py
bluepyefe/reader.py
bluepyefe/recording.py
bluepyefe/rheobase.py
bluepyefe/target.py
bluepyefe/tools.py
bluepyefe/translate_legacy_config.py
bluepyefe/ecode/DeHyperPol.py
bluepyefe/ecode/HyperDePol.py
bluepyefe/ecode/SpikeRec.py
bluepyefe/ecode/__init__.py
bluepyefe/ecode/negCheops.py
bluepyefe/ecode/posCheops.py
bluepyefe/ecode/ramp.py
bluepyefe/ecode/sAHP.py
bluepyefe/ecode/sineSpec.py
bluepyefe/ecode/step.py
bluepyefe/ecode/tools.py
bluepyefe/igorpy/__init__.py
bluepyefe-2.3.52.dist-info/licenses/AUTHORS.txt
bluepyefe-2.3.52.dist-info/licenses/LICENSE.txt
bluepyefe-2.3.52.dist-info/METADATA
bluepyefe-2.3.52.dist-info/WHEEL
bluepyefe-2.3.52.dist-info/top_level.txt
bluepyefe-2.3.52.dist-info/RECORD
