Metadata-Version: 2.4
Name: bluepyefe
Version: 2.3.52
Summary: Blue Brain Python E-feature extraction
Author-email: "Blue Brain Project, EPFL" <werner.vangeit@epfl.ch>
License: BluePyEfe - Bluebrain Python E-feature extraction Library
Project-URL: Homepage, https://github.com/openbraininstitute/BluePyEfe
Project-URL: Source, https://github.com/openbraininstitute/BluePyEfe
Project-URL: Repository, https://github.com/openbraininstitute/BluePyEfe.git
Project-URL: Tracker, https://github.com/openbraininstitute/BluePyEfe/issues
Project-URL: Documentation, https://bluepyefe.readthedocs.io/en/latest
Keywords: neuroscience,BlueBrainProject
Classifier: Development Status :: 4 - Beta
Classifier: Environment :: Console
Classifier: License :: OSI Approved :: GNU Lesser General Public License v3 (LGPLv3)
Classifier: Programming Language :: Python :: 3
Classifier: Operating System :: POSIX
Classifier: Topic :: Scientific/Engineering
Classifier: Topic :: Utilities
Requires-Python: >=3.11
License-File: LICENSE.txt
License-File: AUTHORS.txt
Requires-Dist: numpy
Requires-Dist: neo
Requires-Dist: matplotlib
Requires-Dist: efel
Requires-Dist: scipy>=1.16.1
Requires-Dist: h5py
Requires-Dist: igor2
Dynamic: license-file
